cprofile_graph/__init__.py
cprofile_graph/cli.py
cprofile_graph-2.0.4.dist-info/METADATA
cprofile_graph-2.0.4.dist-info/RECORD
cprofile_graph-2.0.4.dist-info/WHEEL
cprofile_graph-2.0.4.dist-info/entry_points.txt
cprofile_graph-2.0.4.dist-info/top_level.txt
