Metadata-Version: 2.1
Name: cprofile-graph
Version: 2.0.4
Summary: cprofile_graph is used to generate visual graphs for Python profiling.
Home-page: https://github.com/campos-ddc/cprofile_graph
Author: Diogo de Campos
Author-email: campos.ddc@gmail.com
License: MIT license
Keywords: cprofile_graph
Platform: UNKNOWN
Classifier: Development Status :: 5 - Production/Stable
Classifier: Intended Audience :: Developers
Classifier: License :: OSI Approved :: MIT License
Classifier: Natural Language :: English
Classifier: Programming Language :: Python :: 2
Classifier: Programming Language :: Python :: 2.7
Classifier: Programming Language :: Python :: 3
Classifier: Programming Language :: Python :: 3.3
Classifier: Programming Language :: Python :: 3.4
Classifier: Programming Language :: Python :: 3.5
Classifier: Programming Language :: Python :: Implementation :: PyPy
Requires-Dist: click (>=6.0)
Requires-Dist: gprof2dot (>=2016.10.13)
Requires-Dist: pygraphviz
